evalipy/__init__.py
evalipy/__main__.py
evalipy/comparator.py
evalipy/metrics.py
evalipy/model.py
evalipy/report.py
evalipy-0.0.5.dist-info/LICENSE
evalipy-0.0.5.dist-info/METADATA
evalipy-0.0.5.dist-info/WHEEL
evalipy-0.0.5.dist-info/entry_points.txt
evalipy-0.0.5.dist-info/top_level.txt
evalipy-0.0.5.dist-info/RECORD
