Metadata-Version: 2.1
Name: evalipy
Version: 0.0.5
Summary: Evalipy is a framework for evaluating & comparing machine learning models.
Author-email: Mehrdad Heshmat <mehrddy@gmail.com>
License: BSD 3-Clause License
Project-URL: Homepage, https://github.com/evalipy/evalipy/
Keywords: ML,Machine Learning,model,evaluation,framework
Classifier: License :: OSI Approved :: BSD License
Classifier: Programming Language :: Python
Classifier: Programming Language :: Python :: 3
Requires-Python: >=3.8
License-File: LICENSE
Requires-Dist: joblib
Requires-Dist: numpy
Requires-Dist: pandas
Requires-Dist: scikit-learn
